spectrumlab/benchmark/__init__.py
spectrumlab/benchmark/__init__.py.bak
spectrumlab/benchmark/base.py
spectrumlab/benchmark/generation_group.py
spectrumlab/benchmark/perception_group.py
spectrumlab/benchmark/semantic_group.py
spectrumlab/benchmark/signal_group.py
spectrumlab/cli/__init__.py
spectrumlab/cli/api.py
spectrumlab/cli/main.py
spectrumlab/cli/py.typed
spectrumlab/config/__init__.py
spectrumlab/config/base_config.py
spectrumlab/evaluator/__init__.py
spectrumlab/evaluator/base.py
spectrumlab/evaluator/choice_evaluator.py
spectrumlab/evaluator/open_evaluator.py
spectrumlab/models/README.md
spectrumlab/models/__init__.py
spectrumlab/models/base.py
spectrumlab/models/base_api.py
spectrumlab/models/claude_api.py
spectrumlab/models/deepseek_api.py
spectrumlab/models/deepseek_vl.py
spectrumlab/models/doubao_api.py
spectrumlab/models/gpt4_v_api.py
spectrumlab/models/gpt4o_api.py
spectrumlab/models/grok_api.py
spectrumlab/models/internvl_api.py
spectrumlab/models/llama_api.py
spectrumlab/models/qwen_vl_api.py
spectrumlab/utils/__init__.py
spectrumlab/utils/image_utils.py
spectrumlab-0.1.2.dist-info/METADATA
spectrumlab-0.1.2.dist-info/WHEEL
spectrumlab-0.1.2.dist-info/entry_points.txt
spectrumlab-0.1.2.dist-info/RECORD
