Metadata-Version: 2.4
Name: spectrumlab
Version: 0.1.2
Summary: A pioneering unified platform designed to systematize and accelerate deep learning research in spectroscopy.
Author-email: Zhuo Yang <yzachary1551@gmail.com>, Tianfan Fu <futianfan@gmail.com>
Keywords: benchmark,chemistry,evaluation,spectroscopy
Requires-Python: >=3.10
Requires-Dist: dotenv>=0.9.9
Requires-Dist: openai>=1.93.0
Provides-Extra: dev
Requires-Dist: black>=23.0.0; extra == 'dev'
Requires-Dist: pre-commit>=4.2.0; extra == 'dev'
Requires-Dist: pytest>=7.4.0; extra == 'dev'
Requires-Dist: ruff>=0.1.0; extra == 'dev'
Provides-Extra: test
Requires-Dist: pytest-asyncio>=1.1.0; extra == 'test'
Requires-Dist: pytest>=8.4.1; extra == 'test'
